arseg/ARDataSet.py
arseg/__init__.py
arseg/active_region.py
arseg/active_region_derived_fields.py
arseg/active_region_parameters.py
arseg/active_region_segments.py
arseg/data.py
arseg/utils.py
arseg-1.0.0.dist-info/LICENSE
arseg-1.0.0.dist-info/METADATA
arseg-1.0.0.dist-info/WHEEL
arseg-1.0.0.dist-info/top_level.txt
arseg-1.0.0.dist-info/RECORD
