Metadata-Version: 2.1
Name: arseg
Version: 1.0.0
Summary: An active region segmentation library
Home-page: https://github.com/SWxTREC/flares_code_tlincke125
Author: Theo Lincke
Author-email: thli2739@colorado.edu
Project-URL: BugTracker, https://github.com/SWxTREC/flares_code_tlincke125/issues
Classifier: Programming Language :: Python :: 3
Classifier: License :: OSI Approved :: MIT License
Classifier: Operating System :: OS Independent
Requires-Python: >=3.6
License-File: LICENSE
